LICENSE
README.md
setup.cfg
setup.py
src/v_tools.egg-info/PKG-INFO
src/v_tools.egg-info/SOURCES.txt
src/v_tools.egg-info/dependency_links.txt
src/v_tools.egg-info/entry_points.txt
src/v_tools.egg-info/not-zip-safe
src/v_tools.egg-info/requires.txt
src/v_tools.egg-info/top_level.txt
src/vtools/__init__.py
src/vtools/cli.py
src/vtools/evaluate.py
src/vtools/filter.py
src/vtools/gcoverage.py
src/vtools/optimized.pyx
src/vtools/stats.py