Metadata-Version: 2.1
Name: v-tools
Version: 1.1.0
Summary: Various tools operating over VCF files
Home-page: https://git.lumc.nl/klinische-genetica/capture-lumc/vtools
Author: Sander Bollen, Redmar van den Berg
Author-email: KG_bioinf@lumc.nl
License: MIT
Platform: UNKNOWN
Classifier: License :: OSI Approved :: MIT License
Classifier: Programming Language :: Python :: 3 :: Only
Classifier: Programming Language :: Python :: 3.6
Classifier: Programming Language :: Python :: 3.7
Classifier: Topic :: Scientific/Engineering :: Bio-Informatics
Requires-Python: >=3.6
